{
  "kind": "collectionType",
  "collectionName": "playlists",
  "info": {
    "singularName": "playlist",
    "pluralName": "playlists",
    "displayName": "Playlist"
  },
  "options": {
    "draftAndPublish": true
  },
  "pluginOptions": {},
  "attributes": {
    "title": {
      "type": "string",
      "required": true
    },
    "slug": {
      "type": "uid",
      "targetField": "title",
      "required": false
    },
    "videos": {
      "type": "relation",
      "relation": "manyToMany",
      "target": "api::video.video",
      "inversedBy": "playlists"
    }
  }
}
